purecpp_chunks_clean_t/__init__.py
purecpp_chunks_clean_t/purecpp_chunks_clean.cpython-310-x86_64-linux-gnu.so
purecpp_chunks_clean_t-0.0.2.dist-info/METADATA
purecpp_chunks_clean_t-0.0.2.dist-info/WHEEL
purecpp_chunks_clean_t-0.0.2.dist-info/top_level.txt
purecpp_chunks_clean_t-0.0.2.dist-info/RECORD
